Metadata-Version: 2.1
Name: python-prompts
Version: 0.0.10
Summary: Convenient for Python users to directly reference the source code of the GPT question template package. / 方便python用户直接引用GPT提问模板包的源代码
Home-page: https://github.com/limaoyi1/GPT-prompt
Author: limaoyi
Author-email: limaoyi@qq.com
Classifier: Programming Language :: Python :: 3
Classifier: License :: OSI Approved :: MIT License
Classifier: Operating System :: OS Independent
License-File: LICENSE
